{"type": "FeatureCollection", "uuids": [865442598, 587724429], "features": [{"type": "Feature", "geometry": {"type": "LineString", "coordinates": [[-48.694802, -26.905213], [-48.694842, -26.905781], [-48.694849, -26.905859], [-48.694871, -26.906289], [-48.694877, -26.906473], [-48.694904, -26.906791], [-48.694954, -26.907287], [-48.694973, -26.907822], [-48.694976, -26.907882], [-48.695011, -26.908327], [-48.695025, -26.908571], [-48.695046, -26.908832]]}, "properties": {"endNode": "R. Agrol\u00e2ndia", "country": "BR", "roadType": 1, "city": "Itaja\u00ed", "delay": 71, "speed": 3.3, "turnType": "NONE", "speedKMH": 11.879999999999999, "uuid": 865442598, "street": "R. Pedro Cristiano de Miranda", "type": "NONE", "segments": [{}, {}, {}, {}, {}, {}, {}, {}, {}, {}, {}], "length": 401, "pubMillis": 1609296381903, "level": 3, "timestamp": "2020-12-29 23:46:21.903000", "dia_semana": "Ter\u00e7a-Feira", "orientacao": "NS"}}, {"type": "Feature", "geometry": {"type": "LineString", "coordinates": [[-48.701806, -26.893245], [-48.701499, -26.887917]]}, "properties": {"endNode": "R. Dr. Reinaldo Schmithausen", "country": "BR", "roadType": 1, "city": "Itaja\u00ed", "delay": 164, "speed": 2.4805555555555556, "turnType": "NONE", "speedKMH": 8.93, "uuid": 587724429, "street": "R. Eredes Serpa", "type": "NONE", "segments": [{}], "length": 591, "pubMillis": 1609296379867, "level": 3, "timestamp": "2020-12-29 23:46:19.867000", "dia_semana": "Ter\u00e7a-Feira", "orientacao": "SN"}}]}